Kalman/__init__.py
Kalman-0.1.3.dist-info/DESCRIPTION.rst
Kalman-0.1.3.dist-info/METADATA
Kalman-0.1.3.dist-info/metadata.json
Kalman-0.1.3.dist-info/RECORD
Kalman-0.1.3.dist-info/top_level.txt
Kalman-0.1.3.dist-info/WHEEL
